_utils.cpython-310-x86_64-linux-gnu.so
python_malicious_url_block/__init__.py
python_malicious_url_block/python_malicious_url_block.py
python_malicious_url_block/_utils/__init__.py
python_malicious_url_block/_utils/binary_search.cpp
python_malicious_url_block-0.1.2.dist-info/AUTHORS.rst
python_malicious_url_block-0.1.2.dist-info/LICENSE
python_malicious_url_block-0.1.2.dist-info/METADATA
python_malicious_url_block-0.1.2.dist-info/WHEEL
python_malicious_url_block-0.1.2.dist-info/top_level.txt
python_malicious_url_block-0.1.2.dist-info/RECORD
