Metadata-Version: 2.1
Name: python-malicious-url-block
Version: 0.1.2
Summary: Python Malicious Url Block check if it is a malicious URL
Home-page: https://github.com/walkmana-25/python-malicious-url-block
Author: walkmana-25
Author-email: walkman.a25@gmail.com
License: MIT license
Keywords: python-malicious-url-block
Classifier: Development Status :: 2 - Pre-Alpha
Classifier: Intended Audience :: Developers
Classifier: License :: OSI Approved :: MIT License
Classifier: Natural Language :: English
Classifier: Programming Language :: Python :: 3
Classifier: Programming Language :: Python :: 3.9
Classifier: Programming Language :: Python :: 3.10
Requires-Python: >=3.6
License-File: LICENSE
License-File: AUTHORS.rst
Requires-Dist: pybind11
